{
	"info": {
		"_postman_id": "24abdbb9-8627-4929-a067-e3b030a1e7de",
		"name": "Kn-Care-App-Giorgi",
		"schema": "https://schema.getpostman.com/json/collection/v2.1.0/collection.json"
	},
	"item": [
		{
			"name": "api/v1/groups",
			"request": {
				"method": "GET",
				"header": [],
				"url": {
					"raw": "http://localhost:8080/api/v1/groups",
					"protocol": "http",
					"host": [
						"localhost"
					],
					"port": "8080",
					"path": [
						"api",
						"v1",
						"groups"
					],
					"query": [
						{
							"key": "page",
							"value": "0",
							"disabled": true
						},
						{
							"key": "size",
							"value": "3",
							"disabled": true
						},
						{
							"key": "name",
							"value": "First",
							"disabled": true
						}
					]
				}
			},
			"response": []
		},
		{
			"name": "api/v1/groups",
			"request": {
				"method": "POST",
				"header": [
					{
						"key": "Content-Type",
						"value": "application/json",
						"type": "text"
					}
				],
				"body": {
					"mode": "raw",
					"raw": "{\n    \"name\": \"First Group\",\n    \"description\": \"Group description\",\n    \"memberIds\": [1,2]\n}"
				},
				"url": {
					"raw": "http://localhost:8080/api/v1/groups",
					"protocol": "http",
					"host": [
						"localhost"
					],
					"port": "8080",
					"path": [
						"api",
						"v1",
						"groups"
					]
				}
			},
			"response": []
		},
		{
			"name": "api/v1/groups without members",
			"request": {
				"method": "POST",
				"header": [
					{
						"key": "Content-Type",
						"value": "application/json",
						"type": "text"
					}
				],
				"body": {
					"mode": "raw",
					"raw": "{\n    \"name\": \"Group 01\",\n    \"description\": \"Group description\"\n}"
				},
				"url": {
					"raw": "http://localhost:8080/api/v1/groups",
					"protocol": "http",
					"host": [
						"localhost"
					],
					"port": "8080",
					"path": [
						"api",
						"v1",
						"groups"
					]
				}
			},
			"response": []
		},
		{
			"name": "api/v1/groups/134",
			"request": {
				"method": "PUT",
				"header": [
					{
						"key": "Content-Type",
						"value": "application/json",
						"type": "text"
					}
				],
				"body": {
					"mode": "raw",
					"raw": "{\n    \"name\": \"updated First Group\",\n    \"description\": \"updated Group description\",\n    \"memberIds\": [1,3]\n\n}"
				},
				"url": {
					"raw": "http://localhost:8080/api/v1/groups/164",
					"protocol": "http",
					"host": [
						"localhost"
					],
					"port": "8080",
					"path": [
						"api",
						"v1",
						"groups",
						"164"
					]
				}
			},
			"response": []
		},
		{
			"name": "api/v1/members",
			"protocolProfileBehavior": {
				"disableBodyPruning": true
			},
			"request": {
				"method": "GET",
				"header": [],
				"body": {
					"mode": "raw",
					"raw": ""
				},
				"url": {
					"raw": "http://localhost:8080/api/v1/members",
					"protocol": "http",
					"host": [
						"localhost"
					],
					"port": "8080",
					"path": [
						"api",
						"v1",
						"members"
					]
				}
			},
			"response": []
		},
		{
			"name": "api/v1/members/1",
			"request": {
				"method": "GET",
				"header": [],
				"url": {
					"raw": "http://localhost:8080/api/v1/members/1",
					"protocol": "http",
					"host": [
						"localhost"
					],
					"port": "8080",
					"path": [
						"api",
						"v1",
						"members",
						"1"
					]
				}
			},
			"response": []
		},
		{
			"name": "api/v1/members",
			"request": {
				"method": "POST",
				"header": [
					{
						"key": "Content-Type",
						"value": "application/json",
						"type": "text"
					}
				],
				"body": {
					"mode": "raw",
					"raw": "{\n    \"onBoardDate\": \"2021-08-04T12:33:34\",\n    \"offBoardDate\": \"2022-08-04T12:33:34\",\n    \"employee\": {\n        \"id\":2\n    },\n    \"role\": {\n        \"id\":1\n    }\n    \n}"
				},
				"url": {
					"raw": "http://localhost:8080/api/v1/members",
					"protocol": "http",
					"host": [
						"localhost"
					],
					"port": "8080",
					"path": [
						"api",
						"v1",
						"members"
					]
				}
			},
			"response": []
		},
		{
			"name": "api/v1/members/2",
			"request": {
				"method": "DELETE",
				"header": [
					{
						"key": "Content-Type",
						"value": "application/json",
						"type": "text"
					}
				],
				"body": {
					"mode": "raw",
					"raw": "{\n    \"id\": 2,\n    \"onBoardDate\": \"2021-08-04T12:33:34\",\n    \"offBoardDate\": \"2022-08-04T12:33:34\",\n    \"employee\": {\n        \"id\":2\n    },\n    \"role\": {\n        \"id\":1\n    }\n    \n}"
				},
				"url": {
					"raw": "http://localhost:8080/api/v1/members/2",
					"protocol": "http",
					"host": [
						"localhost"
					],
					"port": "8080",
					"path": [
						"api",
						"v1",
						"members",
						"2"
					]
				}
			},
			"response": []
		},
		{
			"name": "api/v1/employees",
			"request": {
				"method": "GET",
				"header": [],
				"url": {
					"raw": "http://localhost:8080/api/v1/employees",
					"protocol": "http",
					"host": [
						"localhost"
					],
					"port": "8080",
					"path": [
						"api",
						"v1",
						"employees"
					]
				}
			},
			"response": []
		},
		{
			"name": "api/v1/employees/1",
			"request": {
				"method": "GET",
				"header": [],
				"url": {
					"raw": "http://localhost:8080/api/v1/employees/1",
					"protocol": "http",
					"host": [
						"localhost"
					],
					"port": "8080",
					"path": [
						"api",
						"v1",
						"employees",
						"1"
					]
				}
			},
			"response": []
		},
		{
			"name": "ngrok.io/api/v1/employees",
			"request": {
				"method": "GET",
				"header": [],
				"url": {
					"raw": "https://0cd6de3cf8ce.ngrok.io/api/v1/employees",
					"protocol": "https",
					"host": [
						"0cd6de3cf8ce",
						"ngrok",
						"io"
					],
					"path": [
						"api",
						"v1",
						"employees"
					]
				}
			},
			"response": []
		}
	]
}